zarrtraj/ZARR.py
zarrtraj/__init__.py
zarrtraj/cache.py
zarrtraj/utils.py
zarrtraj/data/COORDINATES_MISSING_H5MD_GROUP_H5MD.h5md
zarrtraj/data/COORDINATES_MISSING_TIME_DSET_H5MD.h5md
zarrtraj/data/COORDINATES_SYNTHETIC_H5MD.h5md
zarrtraj/data/COORDINATES_VARIED_STEPS_H5MD.h5md
zarrtraj/data/__init__.py
zarrtraj/data/create_COORDINATES_MISSING_H5MD_GROUP.py
zarrtraj/data/create_COORDINATES_MISSING_TIME_DSET.py
zarrtraj/data/create_COORDINATES_SYNTHETIC.py
zarrtraj/data/create_COORDINATES_VARIED_STEPS.py
zarrtraj/data/create_ZARRTRAJ_xvf.py
zarrtraj/data/write_aligned_compressed_disk_h5md.py
zarrtraj/data/write_aligned_compressed_disk_zarrmd.py
zarrtraj/data/write_aligned_compressed_s3_zarrmd.py
zarrtraj/data/write_aligned_uncompressed_disk_h5md.py
zarrtraj/data/write_aligned_uncompressed_disk_zarrmd.py
zarrtraj/data/write_aligned_uncompressed_s3_zarrmd.py
zarrtraj/data/write_aligned_yiip_xtc.py
zarrtraj/data/COORDINATES_MISSING_H5MD_GROUP_ZARRMD.zarrmd/.zattrs
zarrtraj/data/COORDINATES_MISSING_H5MD_GROUP_ZARRMD.zarrmd/.zgroup
zarrtraj/data/COORDINATES_MISSING_H5MD_GROUP_ZARRMD.zarrmd/observables/.zattrs
zarrtraj/data/COORDINATES_MISSING_H5MD_GROUP_ZARRMD.zarrmd/observables/.zgroup
zarrtraj/data/COORDINATES_MISSING_H5MD_GROUP_ZARRMD.zarrmd/observables/occupancy/.zattrs
zarrtraj/data/COORDINATES_MISSING_H5MD_GROUP_ZARRMD.zarrmd/observables/occupancy/.zgroup
zarrtraj/data/COORDINATES_MISSING_H5MD_GROUP_ZARRMD.zarrmd/observables/occupancy/value/.zarray
zarrtraj/data/COORDINATES_MISSING_H5MD_GROUP_ZARRMD.zarrmd/observables/occupancy/value/.zattrs
zarrtraj/data/COORDINATES_MISSING_H5MD_GROUP_ZARRMD.zarrmd/observables/occupancy/value/0.0
zarrtraj/data/COORDINATES_MISSING_H5MD_GROUP_ZARRMD.zarrmd/particles/.zattrs
zarrtraj/data/COORDINATES_MISSING_H5MD_GROUP_ZARRMD.zarrmd/particles/.zgroup
zarrtraj/data/COORDINATES_MISSING_H5MD_GROUP_ZARRMD.zarrmd/particles/trajectory/.zattrs
zarrtraj/data/COORDINATES_MISSING_H5MD_GROUP_ZARRMD.zarrmd/particles/trajectory/.zgroup
zarrtraj-0.3.2.dist-info/licenses/AUTHORS.md
zarrtraj-0.3.2.dist-info/licenses/LICENSE
zarrtraj-0.3.2.dist-info/METADATA
zarrtraj-0.3.2.dist-info/WHEEL
zarrtraj-0.3.2.dist-info/top_level.txt
zarrtraj-0.3.2.dist-info/RECORD
