Metadata-Version: 2.4
Name: zarrtraj
Version: 0.3.2
Summary: This is a kit that provides the ability to read and write trajectory data in the Zarr file format
Author-email: Lawson Woods <ljwoods2@asu.edu>
Maintainer-email: Lawson Woods <ljwoods2@asu.edu>
License: Copyright 2024 Lawson Woods
Keywords: molecular simulations
Requires-Python: >=3.10.0
License-File: LICENSE
License-File: AUTHORS.md
Requires-Dist: MDAnalysis>=2.1.0
Requires-Dist: zarr<3.0,>=2.11.0
Requires-Dist: kerchunk>=0.2.6
Requires-Dist: h5py>=3.11.0
Requires-Dist: s3fs>=2024.3.0
Requires-Dist: gcsfs>=2024.6.1
Requires-Dist: adlfs>=2024.7.0
Provides-Extra: test
Requires-Dist: pytest>=7.4.0; extra == "test"
Requires-Dist: pytest-xdist>=3.5.0; extra == "test"
Requires-Dist: pytest-cov>=4.1.0; extra == "test"
Requires-Dist: MDAnalysisTests>=2.1.0; extra == "test"
Requires-Dist: moto[server]>=5.0.3; extra == "test"
Requires-Dist: pip; extra == "test"
Requires-Dist: codecov; extra == "test"
Provides-Extra: doc
Requires-Dist: sphinx; extra == "doc"
Requires-Dist: sphinx_rtd_theme; extra == "doc"
Dynamic: license-file
